{
  "items": [
    {
      "key": "auth_note_1758839265",
      "value": "Testing MCP Memory Keeper integration with JWT authentication",
      "category": "note",
      "priority": "normal",
      "channel": "ccom-ccom",
      "metadata": {},
      "id": "auth_note_1758839265_1758839265",
      "timestamp": "2025-09-25T18:27:45.721619",
      "session_id": "default"
    },
    {
      "key": "auth_note_1758839270",
      "value": "Decided to use 15-minute access tokens with refresh tokens",
      "category": "note",
      "priority": "normal",
      "channel": "ccom-ccom",
      "metadata": {},
      "id": "auth_note_1758839270_1758839270",
      "timestamp": "2025-09-25T18:27:50.590451",
      "session_id": "default"
    },
    {
      "key": "deployment_progress_1758839633",
      "value": "Executed: deploy to production ",
      "category": "progress",
      "priority": "normal",
      "channel": "ccom-ccom",
      "metadata": {},
      "id": "deployment_progress_1758839633_1758839633",
      "timestamp": "2025-09-25T18:33:53.581853",
      "session_id": "default"
    },
    {
      "key": "workflow-quality_progress_1758839672",
      "value": "Started quality workflow",
      "category": "progress",
      "priority": "normal",
      "channel": "ccom-ccom",
      "metadata": {},
      "id": "workflow-quality_progress_1758839672_1758839672",
      "timestamp": "2025-09-25T18:34:32.726248",
      "session_id": "default"
    },
    {
      "key": "quality_progress_1758923608",
      "value": "Command: test universal capture system",
      "category": "progress",
      "priority": "normal",
      "channel": "ccom-ccom",
      "metadata": {
        "input": "test universal capture system",
        "timestamp": "2025-09-26T17:53:28.393273"
      },
      "id": "quality_progress_1758923608_1758923608",
      "timestamp": "2025-09-26T17:53:28.407273",
      "session_id": "default"
    },
    {
      "key": "quality_progress_1758923608",
      "value": "Command: test universal capture system",
      "category": "progress",
      "priority": "normal",
      "channel": "ccom-ccom",
      "metadata": {
        "input": "test universal capture system",
        "timestamp": "2025-09-26T17:53:28.409565"
      },
      "id": "quality_progress_1758923608_1758923608",
      "timestamp": "2025-09-26T17:53:28.427051",
      "session_id": "default"
    }
  ],
  "sessions": [],
  "channels": {
    "ccom-ccom": {
      "created": "2025-09-25T18:27:45.721619",
      "item_count": 6,
      "last_activity": "2025-09-26T17:53:28.427051"
    }
  },
  "checkpoints": {
    "auth-feature-v1": {
      "name": "auth-feature-v1",
      "description": "CCOM checkpoint for ccom",
      "created": "2025-09-25T18:27:59.495508",
      "items_count": 2,
      "channels": [
        "ccom-ccom"
      ],
      "snapshot": {
        "items": [
          {
            "key": "auth_note_1758839265",
            "value": "Testing MCP Memory Keeper integration with JWT authentication",
            "category": "note",
            "priority": "normal",
            "channel": "ccom-ccom",
            "metadata": {},
            "id": "auth_note_1758839265_1758839265",
            "timestamp": "2025-09-25T18:27:45.721619",
            "session_id": "default"
          },
          {
            "key": "auth_note_1758839270",
            "value": "Decided to use 15-minute access tokens with refresh tokens",
            "category": "note",
            "priority": "normal",
            "channel": "ccom-ccom",
            "metadata": {},
            "id": "auth_note_1758839270_1758839270",
            "timestamp": "2025-09-25T18:27:50.590451",
            "session_id": "default"
          }
        ],
        "channels": {
          "ccom-ccom": {
            "created": "2025-09-25T18:27:45.721619",
            "item_count": 2,
            "last_activity": "2025-09-25T18:27:50.590451"
          }
        }
      }
    }
  }
}